skibidi_orm-0.1.35.dist-info/METADATA
skibidi_orm-0.1.35.dist-info/WHEEL
skibidi_orm-0.1.35.dist-info/entry_points.txt
skibidi_orm/__init__.py
skibidi_orm/cli/log/revision_inspection.py
skibidi_orm/cli/log/tree.py
skibidi_orm/cli/migration_file_creator.py
skibidi_orm/cli/run.py
skibidi_orm/cli/utils.py
skibidi_orm/exceptions/cli_exceptions.py
skibidi_orm/exceptions/config_exceptions.py
skibidi_orm/exceptions/constraints.py
skibidi_orm/exceptions/db_mutator_exceptions.py
skibidi_orm/exceptions/operations.py
skibidi_orm/migration_engine/__init__.py
skibidi_orm/migration_engine/adapters/__init__.py
skibidi_orm/migration_engine/adapters/base_adapter.py
skibidi_orm/migration_engine/adapters/database_objects/__init__.py
skibidi_orm/migration_engine/adapters/database_objects/constraints.py
skibidi_orm/migration_engine/adapters/database_objects/migration_element.py
skibidi_orm/migration_engine/adapters/postgres_adapter.py
skibidi_orm/migration_engine/adapters/postgres_typing.py
skibidi_orm/migration_engine/adapters/providers.py
skibidi_orm/migration_engine/adapters/sqlite3_adapter.py
skibidi_orm/migration_engine/adapters/sqlite3_typing.py
skibidi_orm/migration_engine/converters/base/interfaces.py
skibidi_orm/migration_engine/converters/postgres/all.py
skibidi_orm/migration_engine/converters/postgres/columns.py
skibidi_orm/migration_engine/converters/postgres/constraints.py
skibidi_orm/migration_engine/converters/postgres/tables.py
skibidi_orm/migration_engine/converters/sqlite3/all.py
skibidi_orm/migration_engine/converters/sqlite3/columns.py
skibidi_orm/migration_engine/converters/sqlite3/constraints.py
skibidi_orm/migration_engine/converters/sqlite3/queries.py
skibidi_orm/migration_engine/converters/sqlite3/tables.py
skibidi_orm/migration_engine/data_mutator/base_data_mutator.py
skibidi_orm/migration_engine/data_mutator/postgres_data_mutator.py
skibidi_orm/migration_engine/data_mutator/sqlite3_data_mutatorr.py
skibidi_orm/migration_engine/db_config/base_config.py
skibidi_orm/migration_engine/db_config/postgres_config.py
skibidi_orm/migration_engine/db_config/sqlite3_config.py
skibidi_orm-0.1.35.dist-info/RECORD
