Metadata-Version: 2.1
Name: SkiBiDi-ORM
Version: 0.1.35
Summary: Python ORM
Author-Email: xDepcio <olek.drwal@gmail.com>, jedrzej-grabski <grabski.dev@gmail.com>, mbienkowski <bienkowski.maksym@gmail.com>
License: MIT
Requires-Python: >=3.12
Requires-Dist: typer>=0.11.0
Requires-Dist: colorama>=0.4.6
Requires-Dist: python-dotenv>=1.0.1
Requires-Dist: freezegun>=1.5.1
Requires-Dist: fastapi>=0.111.0
Requires-Dist: prompt-toolkit>=3.0.45
Requires-Dist: black>=24.4.2
Requires-Dist: psycopg2-binary>=2.9.9
Requires-Dist: pdoc3>=0.10.0
